mpr/__init__.py
mpr/__main__.py
mpr/mpr.py
mpr/watcher.py
mpr/xrun.py
mpr-1.34.dist-info/METADATA
mpr-1.34.dist-info/WHEEL
mpr-1.34.dist-info/entry_points.txt
mpr-1.34.dist-info/top_level.txt
mpr-1.34.dist-info/RECORD
