Metadata-Version: 2.4
Name: mpr
Version: 1.34
Summary: Wrapper for MicroPython mpremote tool
Author-email: Mark Blakeney <mark.blakeney@bullet-systems.net>
License-Expression: GPL-3.0-or-later
Project-URL: Homepage, https://github.com/bulletmark/mpr
Keywords: micropython,mpremote,webrepl,ampy,rshell,mpfshell,upyloader,upydev,thonny
Classifier: Programming Language :: Python :: 3
Requires-Python: >=3.8
Requires-Dist: argcomplete
Requires-Dist: platformdirs
Requires-Dist: argparse-from-file
Requires-Dist: inotify_simple; platform_system == "Linux"
Requires-Dist: importlib-metadata; python_version < "3.8"
Provides-Extra: all
Requires-Dist: mpremote; extra == "all"
Requires-Dist: mpy-cross; extra == "all"
Provides-Extra: shell
Requires-Dist: argcomplete; extra == "shell"
